pypcode-3.3.3.dist-info/RECORD
pypcode-3.3.3.dist-info/WHEEL
pypcode-3.3.3.dist-info/top_level.txt
pypcode-3.3.3.dist-info/METADATA
pypcode-3.3.3.dist-info/licenses/LICENSE.txt
pypcode/pypcode_native.cpp
pypcode/__init__.py
pypcode/__version__.py
pypcode/pypcode_native.pyi
pypcode/py.typed
pypcode/pypcode_native.cpython-310-darwin.so
pypcode/__main__.py
pypcode/printing.py
pypcode/bin/sleigh
pypcode/sleigh/emulate.hh
pypcode/sleigh/slaformat.cc
pypcode/sleigh/slghpattern.cc
pypcode/sleigh/opbehavior.hh
pypcode/sleigh/xml.y
pypcode/sleigh/space.cc
pypcode/sleigh/slgh_compile.hh
pypcode/sleigh/context.hh
pypcode/sleigh/sleigh.hh
pypcode/sleigh/pcoderaw.hh
pypcode/sleigh/slghscan.l
pypcode/sleigh/slghparse.cc
pypcode/sleigh/filemanage.hh
pypcode/sleigh/types.h
pypcode/sleigh/slgh_compile.cc
pypcode/sleigh/Makefile
pypcode/sleigh/sleigh.cc
pypcode/sleigh/context.cc
pypcode/sleigh/pcoderaw.cc
pypcode/sleigh/filemanage.cc
pypcode/sleigh/slghparse.hh
pypcode/sleigh/emulate.cc
pypcode/sleigh/slaformat.hh
pypcode/sleigh/slghpattern.hh
pypcode/sleigh/pcodeparse.y
pypcode/sleigh/slghscan.cc
pypcode/sleigh/space.hh
pypcode/sleigh/opbehavior.cc
pypcode/sleigh/compression.cc
pypcode/sleigh/slghpatexpress.hh
pypcode/sleigh/slghsymbol.hh
pypcode/sleigh/loadimage.hh
pypcode/sleigh/sleighbase.cc
pypcode/sleigh/float.cc
pypcode/sleigh/semantics.cc
pypcode/sleigh/opcodes.hh
pypcode/sleigh/error.hh
pypcode/sleigh/pcodeparse.hh
pypcode/sleigh/translate.hh
pypcode/sleigh/loadimage_bfd.hh
pypcode/sleigh/xml.cc
pypcode/sleigh/globalcontext.hh
pypcode/sleigh/marshal.hh
pypcode/sleigh/pcodecompile.cc
pypcode/sleigh/memstate.hh
pypcode/sleigh/address.hh
pypcode/sleigh/pcodeparse.cc
pypcode/sleigh/slghparse.y
pypcode/sleigh/loadimage_bfd.cc
pypcode/sleigh/translate.cc
pypcode/sleigh/globalcontext.cc
pypcode/sleigh/xml.hh
pypcode/sleigh/memstate.cc
pypcode/sleigh/pcodecompile.hh
pypcode/sleigh/address.cc
pypcode/sleigh/marshal.cc
pypcode/sleigh/compression.hh
pypcode/sleigh/slghpatexpress.cc
pypcode/sleigh/slghsymbol.cc
pypcode/sleigh/float.hh
pypcode/sleigh/sleighbase.hh
